keyboardlayout/__init__.py
keyboardlayout/common.py
keyboardlayout/key.py
keyboardlayout/version.py
keyboardlayout/layouts/__init__.py
keyboardlayout/layouts/azerty_laptop.yaml
keyboardlayout/layouts/qwerty.yaml
keyboardlayout/pygame/__init__.py
keyboardlayout/pygame/key.py
keyboardlayout/pygame/keyboardlayout.py
keyboardlayout/tkinter/__init__.py
keyboardlayout/tkinter/key.py
keyboardlayout/tkinter/keyboardlayout.py
keyboardlayout-2.0.1.dist-info/LICENSE
keyboardlayout-2.0.1.dist-info/METADATA
keyboardlayout-2.0.1.dist-info/WHEEL
keyboardlayout-2.0.1.dist-info/top_level.txt
keyboardlayout-2.0.1.dist-info/RECORD
