Metadata-Version: 2.1
Name: keyboardlayout
Version: 2.0.1
Summary: A python library to display different keyboards
Home-page: https://github.com/spacether/keyboardlayout
Author: Justin Black
License: UNKNOWN
Keywords: keyboard,qwerty,layout,azerty,pygame,tkinter,accessibility
Platform: UNKNOWN
Classifier: License :: OSI Approved :: MIT License
Classifier: Programming Language :: Python :: 3
Classifier: Intended Audience :: End Users/Desktop
Classifier: Operating System :: Microsoft :: Windows
Classifier: Operating System :: POSIX
Classifier: Operating System :: MacOS
Classifier: Topic :: Software Development :: Libraries :: Python Modules
Classifier: Topic :: Multimedia :: Graphics
Classifier: Topic :: Games/Entertainment :: Simulation
Classifier: Development Status :: 5 - Production/Stable
Requires-Python: >=3.7
Provides-Extra: dev
